{"tier": 2, "error": null, "params": {"dates": [{"endDate": "12-31-2022", "recurring": false, "startDate": "01-01-2021", "yearRange": [1950, 2050]}], "layers": [{"layer": "FparExtra_QC", "product": "MCD15A3H.061"}, {"layer": "FparLai_QC", "product": "MCD15A3H.061"}, {"layer": "FparStdDev_500m", "product": "MCD15A3H.061"}, {"layer": "Fpar_500m", "product": "MCD15A3H.061"}, {"layer": "LaiStdDev_500m", "product": "MCD15A3H.061"}, {"layer": "Lai_500m", "product": "MCD15A3H.061"}], "output": {"format": {"type": "geotiff"}}, "coordinates": [{"id": "EllerbeClub", "latitude": 36.0194, "longitude": -78.8948}, {"id": "EllerbeGlenn", "latitude": 36.0593, "longitude": -78.8325}, {"id": "NHC", "latitude": 35.9795, "longitude": -79.0018}]}, "status": "processing", "created": "2023-03-10T17:23:55.800251", "task_id": "56fd704a-9177-45b9-81b0-ea44cde663c1", "updated": "2023-03-10T17:28:10.903758", "user_id": "jbehrens33@gmail.com", "estimate": {"request_size": 546, "request_memory": 1}, "retry_at": null, "has_swath": false, "task_name": "ECGS_NHC_try2_3-10-2023", "task_type": "point", "api_version": null, "svc_version": "3.26", "web_version": "3.26", "has_nsidc_daac": false, "expires_on": "2023-04-09T17:28:10.903758", "attempts": 1}
